ruteni/__init__.py
ruteni/__main__.py
ruteni/app.py
ruteni/config.py
ruteni/content.py
ruteni/endpoints.py
ruteni/exceptions.py
ruteni/observable.py
ruteni/quart.py
ruteni/responses.py
ruteni/status.py
ruteni/tasks.py
ruteni/werkzeug.py
ruteni/apis/__init__.py
ruteni/apis/schema.py
ruteni/apis/users.py
ruteni/apis/auth/__init__.py
ruteni/apis/auth/google.py
ruteni/apis/auth/session.py
ruteni/apis/auth/token.py
ruteni/apis/auth/twitter.py
ruteni/apis/logging/__init__.py
ruteni/apis/logging/js/node_modules/workbox-build/build/templates/sw-template.d.ts
ruteni/apis/logging/js/node_modules/workbox-build/build/templates/sw-template.js
ruteni/apis/logging/js/node_modules/workbox-build/src/templates/sw-template.ts
ruteni/apis/security/__init__.py
ruteni/apis/security/js/node_modules/workbox-build/build/templates/sw-template.d.ts
ruteni/apis/security/js/node_modules/workbox-build/build/templates/sw-template.js
ruteni/apis/security/js/node_modules/workbox-build/src/templates/sw-template.ts
ruteni/apps/__init__.py
ruteni/apps/registration/__init__.py
ruteni/apps/registration/resources/index.html
ruteni/apps/registration/resources/resources.js
ruteni/apps/registration/resources/resources.json
ruteni/apps/store/__init__.py
ruteni/apps/store/resources/favicon.ico
ruteni/apps/store/resources/index.html
ruteni/apps/store/resources/en-US/manifest.json
ruteni/apps/store/resources/en-US/sw.js
ruteni/apps/store/resources/fr-FR/manifest.json
ruteni/apps/store/resources/fr-FR/sw.js
ruteni/core/__init__.py
ruteni/core/app.py
ruteni/core/lifespan.py
ruteni/core/types.py
ruteni/core/websocket.py
ruteni/dist/manifests/@ruteni/blaze/v1.json
ruteni/dist/manifests/@ruteni/component/v1.json
ruteni/dist/manifests/@ruteni/logging/v1.json
ruteni/dist/manifests/@ruteni/pwa/v1.json
ruteni/dist/manifests/@ruteni/quotquot/v1.json
ruteni/dist/manifests/@ruteni/registration/v1.json
ruteni/dist/manifests/@ruteni/security/v1.json
ruteni/dist/manifests/@ruteni/site/v1.json
ruteni-0.8.0.dist-info/METADATA
ruteni-0.8.0.dist-info/WHEEL
ruteni-0.8.0.dist-info/entry_points.txt
ruteni-0.8.0.dist-info/top_level.txt
ruteni-0.8.0.dist-info/RECORD
