Metadata-Version: 2.1
Name: ruteni
Version: 0.8.0
Summary: Thin layer over Starlette
Home-page: UNKNOWN
Author: Johnny Accot
License: UNKNOWN
Platform: UNKNOWN
Classifier: Programming Language :: Python :: 3
Classifier: License :: OSI Approved :: MIT License
Classifier: Operating System :: OS Independent
Requires-Python: >=3.6
Requires-Dist: aiodns
Requires-Dist: aioredis
Requires-Dist: aiosmtplib
Requires-Dist: aiosmtpd
Requires-Dist: aiosqlite
Requires-Dist: anyio
Requires-Dist: anytree
Requires-Dist: apscheduler
Requires-Dist: argon2-cffi
Requires-Dist: asgiref
Requires-Dist: asyncssh
Requires-Dist: authlib
Requires-Dist: babel
Requires-Dist: boolean.py
Requires-Dist: databases
Requires-Dist: html5lib
Requires-Dist: httpx
Requires-Dist: itsdangerous
Requires-Dist: jinja2
Requires-Dist: jwcrypto
Requires-Dist: limits
Requires-Dist: marshmallow
Requires-Dist: pillow
Requires-Dist: pynng
Requires-Dist: python-socketio
Requires-Dist: pyrfc3339
Requires-Dist: sqlalchemy
Requires-Dist: sqlalchemy-utils
Requires-Dist: starlette
Requires-Dist: tabulate
Requires-Dist: toposort
Requires-Dist: totates
Requires-Dist: transitions
Requires-Dist: uvicorn
Requires-Dist: webcolors
Requires-Dist: websockets
Requires-Dist: werkzeug
Requires-Dist: zxcvbn
